[
  {
    "date": "2025-05-19",
    "day": "Monday",
    "avg_temp_f": 50.51
  },
  {
    "date": "2025-05-20",
    "day": "Tuesday",
    "avg_temp_f": 50.63
  },
  {
    "date": "2025-05-21",
    "day": "Wednesday",
    "avg_temp_f": 50.48
  },
  {
    "date": "2025-05-22",
    "day": "Thursday",
    "avg_temp_f": 49.87
  },
  {
    "date": "2025-05-23",
    "day": "Friday",
    "avg_temp_f": 49.09
  },
  {
    "date": "2025-05-24",
    "day": "Saturday",
    "avg_temp_f": 48.79
  },
  {
    "date": "2025-05-25",
    "day": "Sunday",
    "avg_temp_f": 48.82
  },
  {
    "date": "2025-05-26",
    "day": "Monday",
    "avg_temp_f": 49.5
  }
]